{"title": "8-Bit to Byte Merger", "name": "LGF_MergeBitsToByte", "description": "This function merge 8 Bits / 8 Boolean variables into one Byte variable.", "type": "FUNCTION", "input": [{"name": "bit7", "type": "Bool", "description": "Input Bit 7 - MSB"}, {"name": "bit6", "type": "Bool", "description": "Input Bit 6"}, {"name": "bit5", "type": "Bool", "description": "Input Bit 5"}, {"name": "bit4", "type": "Bool", "description": "Input Bit 4"}, {"name": "bit3", "type": "Bool", "description": "Input Bit 3"}, {"name": "bit2", "type": "Bool", "description": "Input Bit 2"}, {"name": "bit1", "type": "Bool", "description": "Input Bit 1"}, {"name": "bit0", "type": "Bool", "description": "Input Bit 0 - LSB"}], "output": [], "in/out": [], "return_value": [{"type": "Byte", "description": "Composite Bit sequence stored as Byte variable"}], "status_codes": {}, "user_defined_types": []}