{"title": "String to DInt Converter", "name": "LGF_StringToInt", "description": "This function converts a variable of data type String into a variable of data type DInt.", "type": "FUNCTION", "input": [{"name": "value", "type": "String", "description": "String value to be converted to Double-Integer. Example: ‘+16927’"}], "output": [], "in/out": [], "return_value": [{"type": "DInt", "description": "Converted Double-Integer value"}], "status_codes": {"16#0000": "STATUS_NO_ERROR"}, "user_defined_types": [], "description_zh": "\n这是一个函数FC，该函数能够将字符串转换为双整数（DInt）类型的数值。函数接受一个字符串类型的输入参数，并返回一个双整数类型的输出值。\\n\\n示例：\\n假设输入的字符串为\\\"+16927\\\"，函数应返回双整数值16927作为转换结果。\\n注意，输入的字符串可以是带符号的，也可以是不带符号的。如果字符串表示的数值超出了双整数类型的范围，函数可能会返回一个错误值。\n\n\n"}