{"title": "Profinet Interface Parameter Reader", "name": "LGF_ReadPnInterfaceParameter", "description": "Provides interface parameters such as IP Address, MAC Address, and PN Name.", "type": "FUNCTION_BLOCK", "input": [{"name": "execute", "type": "Bool", "description": "Rising edge starts action once"}, {"name": "hardwareId", "type": "HW_ANY", "description": "Hardware ID of the Interface where the parameter should be read"}], "output": [{"name": "done", "type": "Bool", "description": "Commanded functionality has been completed successfully"}, {"name": "busy", "type": "Bool", "description": "FB is not finished, new output values can be expected"}, {"name": "error", "type": "Bool", "description": "An error occurred during the execution of the FB"}, {"name": "status", "type": "DWord", "description": "Status of the FB and error identification"}, {"name": "address", "type": "IP_V4", "description": "IP Address from interface"}, {"name": "subnetMask", "type": "IP_V4", "description": "Subnet mask from interface"}, {"name": "standardGateway", "type": "IP_V4", "description": "Standard gateway address from interface"}, {"name": "macAddress", "type": "Array[0..5] of Byte", "description": "MAC Address from interface"}, {"name": "pnName", "type": "String", "description": "Profinet name from interface"}], "in/out": [], "return_value": [], "status_codes": {"16#0000": "STATUS_EXECUTION_FINISHED: Execution finished without errors", "16#7000": "STATUS_NO_CALL: No job being currently processed", "16#7001": "STATUS_FIRST_CALL: First call after incoming new job", "16#7002": "STATUS_SUBSEQUENT_CALL: Subsequent call during active processing", "16#9000": "ERR_UNDEFINED_STATE: Due to an undefined state in state machine"}, "user_defined_types": [], "description_zh": "\n一个函数块FB，用于读取Profinet接口的参数，包括IP地址、子网掩码、默认网关、MAC地址和PN名称。当触发输入execute时，FB将开始执行读取操作。FB使用状态机来管理读取过程，包括读取记录和处理记录两个状态。在读取记录状态，FB将调用一个子函数块RDREC来读取接口参数。在处理记录状态，FB将解析读取到的记录并更新输出参数。当操作完成时，FB将设置输出参数done为TRUE，表示操作成功完成。如果过程中发生错误，FB将设置输出参数error为TRUE，并返回错误状态。状态代码用于表示FB的执行状态和错误信息。\n\n\n"}